local_package_visualizer/__init__.py
local_package_visualizer/cli.py
local_package_visualizer/analyser/__init__.py
local_package_visualizer/analyser/cycle_detector.py
local_package_visualizer/analyser/dead_code_detector.py
local_package_visualizer/analyser/module_analyzer.py
local_package_visualizer/analyser/split_suggester.py
local_package_visualizer/analyser/visualizer.py
local_package_visualizer/parser/__init__.py
local_package_visualizer/parser/ast_parser.py
local_package_visualizer/parser/dynamic_import_detector.py
local_package_visualizer/parser/graph_builder.py
local_package_visualizer/parser/import_resolver.py
local_package_visualizer-0.1.3.dist-info/METADATA
local_package_visualizer-0.1.3.dist-info/WHEEL
local_package_visualizer-0.1.3.dist-info/entry_points.txt
local_package_visualizer-0.1.3.dist-info/top_level.txt
local_package_visualizer-0.1.3.dist-info/RECORD
