Metadata-Version: 2.4
Name: local-package-visualizer
Version: 0.1.3
Summary: Local package dependency visualizer tool
License: MIT
Requires-Python: >=3.8
